Metadata-Version: 2.1
Name: pyrichlet
Version: 0.0.3
Summary: A package for density estimation and clustering using infinite gaussian mixtures with stick-breaking weighting structures
Home-page: https://github.com/cabo40/pyrichlet
Author: Fidel Selva
Author-email: cfso100@gmail.com
License: Apache License, Version 2.0
Project-URL: Bug Tracker, https://github.com/cabo40/pyrichlet/issues
Project-URL: Documentation, https://pyrichlet.readthedocs.io
Project-URL: Source Code, https://github.com/cabo40/pyrichlet
Platform: UNKNOWN
Classifier: Intended Audience :: Science/Research
Classifier: Programming Language :: Python
Classifier: Programming Language :: Python :: 3
Classifier: Programming Language :: Python :: 3.7
Classifier: Programming Language :: Python :: 3.8
Classifier: Programming Language :: Python :: 3.9
Classifier: License :: OSI Approved :: Apache Software License
Classifier: Operating System :: OS Independent
Requires-Python: >=3.6
License-File: LICENSE
Requires-Dist: numpy
Requires-Dist: scipy
Requires-Dist: pandas
Requires-Dist: scikit-learn
Provides-Extra: tqdm
Requires-Dist: tqdm ; extra == 'tqdm'
